[
  {
    "referente_a": "05/05/2026",
    "coletado_em": "2026-05-05T15:15:12.664931",
    "produto": "cafe",
    "tipo": "arabica",
    "valor": 1759.77,
    "unidade": "saca",
    "moeda": "BRL"
  },
  {
    "referente_a": "05/05/2026",
    "coletado_em": "2026-05-05T15:15:12.664931",
    "produto": "cafe",
    "tipo": "conillon",
    "valor": 910.36,
    "unidade": "saca",
    "moeda": "BRL"
  },
  {
    "referente_a": "05/05/2026",
    "coletado_em": "2026-05-05T19:05:33.218516",
    "produto": "cafe",
    "tipo": "arabica",
    "valor": 1759.77,
    "unidade": "saca",
    "moeda": "BRL"
  },
  {
    "referente_a": "05/05/2026",
    "coletado_em": "2026-05-05T19:05:33.218516",
    "produto": "cafe",
    "tipo": "conillon",
    "valor": 910.36,
    "unidade": "saca",
    "moeda": "BRL"
  },
  {
    "referente_a": "06/05/2026",
    "coletado_em": "2026-05-06T01:36:05.013019",
    "produto": "cafe",
    "tipo": "arabica",
    "valor": 1758.67,
    "unidade": "saca",
    "moeda": "BRL"
  },
  {
    "referente_a": "06/05/2026",
    "coletado_em": "2026-05-06T01:36:05.013019",
    "produto": "cafe",
    "tipo": "conillon",
    "valor": 924.65,
    "unidade": "saca",
    "moeda": "BRL"
  },
  {
    "referente_a": "06/05/2026",
    "coletado_em": "2026-05-06T04:37:46.679033",
    "produto": "cafe",
    "tipo": "arabica",
    "valor": 1758.67,
    "unidade": "saca",
    "moeda": "BRL"
  },
  {
    "referente_a": "06/05/2026",
    "coletado_em": "2026-05-06T04:37:46.679033",
    "produto": "cafe",
    "tipo": "conillon",
    "valor": 924.65,
    "unidade": "saca",
    "moeda": "BRL"
  },
  {
    "referente_a": "06/05/2026",
    "coletado_em": "2026-05-06T08:10:03.098691",
    "produto": "cafe",
    "tipo": "arabica",
    "valor": 1758.67,
    "unidade": "saca",
    "moeda": "BRL"
  },
  {
    "referente_a": "06/05/2026",
    "coletado_em": "2026-05-06T08:10:03.098691",
    "produto": "cafe",
    "tipo": "conillon",
    "valor": 924.65,
    "unidade": "saca",
    "moeda": "BRL"
  },
  {
    "referente_a": "06/05/2026",
    "coletado_em": "2026-05-06T12:27:47.195468",
    "produto": "cafe",
    "tipo": "arabica",
    "valor": 1758.67,
    "unidade": "saca",
    "moeda": "BRL"
  },
  {
    "referente_a": "06/05/2026",
    "coletado_em": "2026-05-06T12:27:47.195468",
    "produto": "cafe",
    "tipo": "conillon",
    "valor": 924.65,
    "unidade": "saca",
    "moeda": "BRL"
  },
  {
    "referente_a": "06/05/2026",
    "coletado_em": "2026-05-06T15:22:51.492323",
    "produto": "cafe",
    "tipo": "arabica",
    "valor": 1758.67,
    "unidade": "saca",
    "moeda": "BRL"
  },
  {
    "referente_a": "06/05/2026",
    "coletado_em": "2026-05-06T15:22:51.492323",
    "produto": "cafe",
    "tipo": "conillon",
    "valor": 924.65,
    "unidade": "saca",
    "moeda": "BRL"
  },
  {
    "referente_a": "06/05/2026",
    "coletado_em": "2026-05-06T19:02:14.812389",
    "produto": "cafe",
    "tipo": "arabica",
    "valor": 1758.67,
    "unidade": "saca",
    "moeda": "BRL"
  },
  {
    "referente_a": "06/05/2026",
    "coletado_em": "2026-05-06T19:02:14.812389",
    "produto": "cafe",
    "tipo": "conillon",
    "valor": 924.65,
    "unidade": "saca",
    "moeda": "BRL"
  },
  {
    "referente_a": "07/05/2026",
    "coletado_em": "2026-05-07T01:36:56.979486",
    "produto": "cafe",
    "tipo": "arabica",
    "valor": 1744.04,
    "unidade": "saca",
    "moeda": "BRL"
  },
  {
    "referente_a": "07/05/2026",
    "coletado_em": "2026-05-07T01:36:56.979486",
    "produto": "cafe",
    "tipo": "conillon",
    "valor": 916.32,
    "unidade": "saca",
    "moeda": "BRL"
  },
  {
    "referente_a": "07/05/2026",
    "coletado_em": "2026-05-07T04:45:04.272046",
    "produto": "cafe",
    "tipo": "arabica",
    "valor": 1744.04,
    "unidade": "saca",
    "moeda": "BRL"
  },
  {
    "referente_a": "07/05/2026",
    "coletado_em": "2026-05-07T04:45:04.272046",
    "produto": "cafe",
    "tipo": "conillon",
    "valor": 916.32,
    "unidade": "saca",
    "moeda": "BRL"
  }
]