[
  {
    "referente_a": "08/06/2026",
    "coletado_em": "2026-06-08T16:25:35.490139",
    "produto": "cafe",
    "tipo": "arabica",
    "valor": 1433.64,
    "unidade": "saca",
    "moeda": "BRL"
  },
  {
    "referente_a": "08/06/2026",
    "coletado_em": "2026-06-08T16:25:35.490139",
    "produto": "cafe",
    "tipo": "conillon",
    "valor": 921.46,
    "unidade": "saca",
    "moeda": "BRL"
  },
  {
    "referente_a": "08/06/2026",
    "coletado_em": "2026-06-08T19:42:35.655573",
    "produto": "cafe",
    "tipo": "arabica",
    "valor": 1395.16,
    "unidade": "saca",
    "moeda": "BRL"
  },
  {
    "referente_a": "08/06/2026",
    "coletado_em": "2026-06-08T19:42:35.655573",
    "produto": "cafe",
    "tipo": "conillon",
    "valor": 948.38,
    "unidade": "saca",
    "moeda": "BRL"
  },
  {
    "referente_a": "09/06/2026",
    "coletado_em": "2026-06-09T02:11:11.357426",
    "produto": "cafe",
    "tipo": "arabica",
    "valor": 1395.16,
    "unidade": "saca",
    "moeda": "BRL"
  },
  {
    "referente_a": "09/06/2026",
    "coletado_em": "2026-06-09T02:11:11.357426",
    "produto": "cafe",
    "tipo": "conillon",
    "valor": 948.38,
    "unidade": "saca",
    "moeda": "BRL"
  },
  {
    "referente_a": "09/06/2026",
    "coletado_em": "2026-06-09T09:09:27.798975",
    "produto": "cafe",
    "tipo": "arabica",
    "valor": 1395.16,
    "unidade": "saca",
    "moeda": "BRL"
  },
  {
    "referente_a": "09/06/2026",
    "coletado_em": "2026-06-09T09:09:27.798975",
    "produto": "cafe",
    "tipo": "conillon",
    "valor": 948.38,
    "unidade": "saca",
    "moeda": "BRL"
  },
  {
    "referente_a": "09/06/2026",
    "coletado_em": "2026-06-09T13:07:50.046805",
    "produto": "cafe",
    "tipo": "arabica",
    "valor": 1395.16,
    "unidade": "saca",
    "moeda": "BRL"
  },
  {
    "referente_a": "09/06/2026",
    "coletado_em": "2026-06-09T13:07:50.046805",
    "produto": "cafe",
    "tipo": "conillon",
    "valor": 948.38,
    "unidade": "saca",
    "moeda": "BRL"
  },
  {
    "referente_a": "09/06/2026",
    "coletado_em": "2026-06-09T16:20:57.838697",
    "produto": "cafe",
    "tipo": "arabica",
    "valor": 1395.16,
    "unidade": "saca",
    "moeda": "BRL"
  },
  {
    "referente_a": "09/06/2026",
    "coletado_em": "2026-06-09T16:20:57.838697",
    "produto": "cafe",
    "tipo": "conillon",
    "valor": 948.38,
    "unidade": "saca",
    "moeda": "BRL"
  },
  {
    "referente_a": "09/06/2026",
    "coletado_em": "2026-06-09T19:26:48.499390",
    "produto": "cafe",
    "tipo": "arabica",
    "valor": 1383.57,
    "unidade": "saca",
    "moeda": "BRL"
  },
  {
    "referente_a": "09/06/2026",
    "coletado_em": "2026-06-09T19:26:48.499390",
    "produto": "cafe",
    "tipo": "conillon",
    "valor": 945.74,
    "unidade": "saca",
    "moeda": "BRL"
  },
  {
    "referente_a": "10/06/2026",
    "coletado_em": "2026-06-10T02:23:33.346357",
    "produto": "cafe",
    "tipo": "arabica",
    "valor": 1383.57,
    "unidade": "saca",
    "moeda": "BRL"
  },
  {
    "referente_a": "10/06/2026",
    "coletado_em": "2026-06-10T02:23:33.346357",
    "produto": "cafe",
    "tipo": "conillon",
    "valor": 945.74,
    "unidade": "saca",
    "moeda": "BRL"
  },
  {
    "referente_a": "10/06/2026",
    "coletado_em": "2026-06-10T09:28:51.628740",
    "produto": "cafe",
    "tipo": "arabica",
    "valor": 1383.57,
    "unidade": "saca",
    "moeda": "BRL"
  },
  {
    "referente_a": "10/06/2026",
    "coletado_em": "2026-06-10T09:28:51.628740",
    "produto": "cafe",
    "tipo": "conillon",
    "valor": 945.74,
    "unidade": "saca",
    "moeda": "BRL"
  },
  {
    "referente_a": "10/06/2026",
    "coletado_em": "2026-06-10T13:38:48.823161",
    "produto": "cafe",
    "tipo": "arabica",
    "valor": 1383.57,
    "unidade": "saca",
    "moeda": "BRL"
  },
  {
    "referente_a": "10/06/2026",
    "coletado_em": "2026-06-10T13:38:48.823161",
    "produto": "cafe",
    "tipo": "conillon",
    "valor": 945.74,
    "unidade": "saca",
    "moeda": "BRL"
  }
]