[
  {
    "referente_a": "09/02/2026",
    "coletado_em": "2026-02-09T07:08:36.179099",
    "produto": "cafe",
    "tipo": "arabica",
    "valor": 1884.66,
    "unidade": "saca",
    "moeda": "BRL"
  },
  {
    "referente_a": "09/02/2026",
    "coletado_em": "2026-02-09T07:08:36.179099",
    "produto": "cafe",
    "tipo": "conillon",
    "valor": 1068.7,
    "unidade": "saca",
    "moeda": "BRL"
  },
  {
    "referente_a": "09/02/2026",
    "coletado_em": "2026-02-09T11:16:29.880395",
    "produto": "cafe",
    "tipo": "arabica",
    "valor": 1884.66,
    "unidade": "saca",
    "moeda": "BRL"
  },
  {
    "referente_a": "09/02/2026",
    "coletado_em": "2026-02-09T11:16:29.880395",
    "produto": "cafe",
    "tipo": "conillon",
    "valor": 1068.7,
    "unidade": "saca",
    "moeda": "BRL"
  },
  {
    "referente_a": "09/02/2026",
    "coletado_em": "2026-02-09T14:54:36.459716",
    "produto": "cafe",
    "tipo": "arabica",
    "valor": 1884.66,
    "unidade": "saca",
    "moeda": "BRL"
  },
  {
    "referente_a": "09/02/2026",
    "coletado_em": "2026-02-09T14:54:36.459716",
    "produto": "cafe",
    "tipo": "conillon",
    "valor": 1068.7,
    "unidade": "saca",
    "moeda": "BRL"
  },
  {
    "referente_a": "09/02/2026",
    "coletado_em": "2026-02-09T18:47:29.547351",
    "produto": "cafe",
    "tipo": "arabica",
    "valor": 1884.66,
    "unidade": "saca",
    "moeda": "BRL"
  },
  {
    "referente_a": "09/02/2026",
    "coletado_em": "2026-02-09T18:47:29.547351",
    "produto": "cafe",
    "tipo": "conillon",
    "valor": 1068.7,
    "unidade": "saca",
    "moeda": "BRL"
  },
  {
    "referente_a": "10/02/2026",
    "coletado_em": "2026-02-10T00:52:50.085299",
    "produto": "cafe",
    "tipo": "arabica",
    "valor": 1861.69,
    "unidade": "saca",
    "moeda": "BRL"
  },
  {
    "referente_a": "10/02/2026",
    "coletado_em": "2026-02-10T00:52:50.085299",
    "produto": "cafe",
    "tipo": "conillon",
    "valor": 1063.5,
    "unidade": "saca",
    "moeda": "BRL"
  },
  {
    "referente_a": "10/02/2026",
    "coletado_em": "2026-02-10T03:13:22.078498",
    "produto": "cafe",
    "tipo": "arabica",
    "valor": 1861.69,
    "unidade": "saca",
    "moeda": "BRL"
  },
  {
    "referente_a": "10/02/2026",
    "coletado_em": "2026-02-10T03:13:22.078498",
    "produto": "cafe",
    "tipo": "conillon",
    "valor": 1063.5,
    "unidade": "saca",
    "moeda": "BRL"
  },
  {
    "referente_a": "10/02/2026",
    "coletado_em": "2026-02-10T07:04:43.194960",
    "produto": "cafe",
    "tipo": "arabica",
    "valor": 1861.69,
    "unidade": "saca",
    "moeda": "BRL"
  },
  {
    "referente_a": "10/02/2026",
    "coletado_em": "2026-02-10T07:04:43.194960",
    "produto": "cafe",
    "tipo": "conillon",
    "valor": 1063.5,
    "unidade": "saca",
    "moeda": "BRL"
  },
  {
    "referente_a": "10/02/2026",
    "coletado_em": "2026-02-10T11:23:17.772644",
    "produto": "cafe",
    "tipo": "arabica",
    "valor": 1861.69,
    "unidade": "saca",
    "moeda": "BRL"
  },
  {
    "referente_a": "10/02/2026",
    "coletado_em": "2026-02-10T11:23:17.772644",
    "produto": "cafe",
    "tipo": "conillon",
    "valor": 1063.5,
    "unidade": "saca",
    "moeda": "BRL"
  },
  {
    "referente_a": "10/02/2026",
    "coletado_em": "2026-02-10T18:51:19.786759",
    "produto": "cafe",
    "tipo": "arabica",
    "valor": 1861.69,
    "unidade": "saca",
    "moeda": "BRL"
  },
  {
    "referente_a": "10/02/2026",
    "coletado_em": "2026-02-10T18:51:19.786759",
    "produto": "cafe",
    "tipo": "conillon",
    "valor": 1063.5,
    "unidade": "saca",
    "moeda": "BRL"
  },
  {
    "referente_a": "11/02/2026",
    "coletado_em": "2026-02-11T00:50:02.714056",
    "produto": "cafe",
    "tipo": "arabica",
    "valor": 1861.64,
    "unidade": "saca",
    "moeda": "BRL"
  },
  {
    "referente_a": "11/02/2026",
    "coletado_em": "2026-02-11T00:50:02.714056",
    "produto": "cafe",
    "tipo": "conillon",
    "valor": 1069.05,
    "unidade": "saca",
    "moeda": "BRL"
  }
]