{
  "ultima_atualizacao": "2026-01-04T14:23:12.805936",
  "data_formatada": "04/01/2026",
  "hora_formatada": "14:23:12",
  "pregao_aberto": false,
  "fonte": "Notícias Agrícolas",
  "cafe": {
    "arabica": {
      "preco": 2171.95,
      "unidade": "saca",
      "peso_kg": 60,
      "moeda": "BRL"
    },
    "robusta": {
      "preco": 1263.38,
      "unidade": "saca",
      "peso_kg": 60,
      "moeda": "BRL"
    },
    "conilon": {
      "preco": 1263.38,
      "unidade": "saca",
      "peso_kg": 60,
      "moeda": "BRL"
    }
  }
}