{
  "ultima_atualizacao": "2026-05-24T11:39:37.422253",
  "data_formatada": "24/05/2026",
  "hora_formatada": "11:39:37",
  "pregao_aberto": false,
  "fonte": "Notícias Agrícolas",
  "cafe": {
    "arabica": {
      "preco": 1612.87,
      "unidade": "saca",
      "peso_kg": 60,
      "moeda": "BRL"
    },
    "robusta": {
      "preco": 941.92,
      "unidade": "saca",
      "peso_kg": 60,
      "moeda": "BRL"
    },
    "conilon": {
      "preco": 941.92,
      "unidade": "saca",
      "peso_kg": 60,
      "moeda": "BRL"
    }
  }
}