{
  "ultima_atualizacao": "2026-01-07T23:59:40.918481",
  "data_formatada": "07/01/2026",
  "hora_formatada": "23:59:40",
  "pregao_aberto": true,
  "fonte": "Notícias Agrícolas",
  "cafe": {
    "arabica": {
      "preco": 2263.04,
      "unidade": "saca",
      "peso_kg": 60,
      "moeda": "BRL"
    },
    "robusta": {
      "preco": 1282.66,
      "unidade": "saca",
      "peso_kg": 60,
      "moeda": "BRL"
    },
    "conilon": {
      "preco": 1282.66,
      "unidade": "saca",
      "peso_kg": 60,
      "moeda": "BRL"
    }
  }
}