{
  "ultima_atualizacao": "2026-05-16T01:32:27.035157",
  "data_formatada": "16/05/2026",
  "hora_formatada": "01:32:27",
  "pregao_aberto": false,
  "fonte": "Notícias Agrícolas",
  "cafe": {
    "arabica": {
      "preco": 1637.88,
      "unidade": "saca",
      "peso_kg": 60,
      "moeda": "BRL"
    },
    "robusta": {
      "preco": 930.15,
      "unidade": "saca",
      "peso_kg": 60,
      "moeda": "BRL"
    },
    "conilon": {
      "preco": 930.15,
      "unidade": "saca",
      "peso_kg": 60,
      "moeda": "BRL"
    }
  }
}